YaDiskClient/YaDiskClient.py
YaDiskClient/__init__.py
YaDiskClient-1.0.1.dist-info/LICENSE
YaDiskClient-1.0.1.dist-info/METADATA
YaDiskClient-1.0.1.dist-info/WHEEL
YaDiskClient-1.0.1.dist-info/top_level.txt
YaDiskClient-1.0.1.dist-info/RECORD
