Metadata-Version: 2.1
Name: YaDiskClient
Version: 1.0.1
Summary: Clent for Yandex.Disk
Home-page: https://github.com/TyVik/YaDiskClient
Author: TyVik
Author-email: tyvik8@gmail.com
License: MIT
Keywords: Yandex.Disk,webdav,client,python,Yandex
Platform: UNKNOWN
Classifier: Development Status :: 5 - Production/Stable
Classifier: Environment :: Console
Classifier: Intended Audience :: Developers
Classifier: Intended Audience :: System Administrators
Classifier: License :: OSI Approved :: MIT License
Classifier: Operating System :: OS Independent
Classifier: Programming Language :: Python :: 2.7
Classifier: Programming Language :: Python :: 3.3
Classifier: Programming Language :: Python :: 3.4
Classifier: Programming Language :: Python :: 3.5
Classifier: Programming Language :: Python :: 3.6
Classifier: Programming Language :: Python :: 3.7
Classifier: Programming Language :: Python :: 3.8
Classifier: Programming Language :: Python :: 3.9
Classifier: Programming Language :: Python :: 3.10
Classifier: Programming Language :: Python
Classifier: Topic :: Internet
Classifier: Topic :: Utilities
Classifier: Topic :: System :: Archiving :: Backup
Requires-Dist: requests
